superstream/__init__.py
superstream/stream.py
superstream/util.py
SuperStream-0.2.6.dist-info/LICENSE
SuperStream-0.2.6.dist-info/METADATA
SuperStream-0.2.6.dist-info/WHEEL
SuperStream-0.2.6.dist-info/top_level.txt
SuperStream-0.2.6.dist-info/RECORD
