Metadata-Version: 2.1
Name: SuperStream
Version: 0.2.6
Summary: A lightweight streaming library, similar to Java stream.
Home-page: https://github.com/Shimada666/super-stream
Author: Shimada666
Author-email: 649940882@qq.com
License: MIT
Project-URL: Documentation, https://github.com/Shimada666/super-stream
Project-URL: Source, https://github.com/Shimada666/super-stream
Project-URL: Changelog, https://github.com/Shimada666/super-stream
Project-URL: Issue Tracker, https://github.com/Shimada666/super-stream/issues
Keywords: stream,lazily evaluated
Platform: any
Classifier: Development Status :: 3 - Alpha
Classifier: Programming Language :: Python :: 3.6
Classifier: Programming Language :: Python :: 3.7
Classifier: Programming Language :: Python :: 3.8
Classifier: Programming Language :: Python :: 3.9
Classifier: License :: OSI Approved :: MIT License
Classifier: Operating System :: OS Independent
Requires-Python: >=3.6
License-File: LICENSE
